ripe_rainbow/__init__.py
ripe_rainbow/decorators.py
ripe_rainbow/errors.py
ripe_rainbow/info.py
ripe_rainbow/loaders.py
ripe_rainbow/main.py
ripe_rainbow/results.py
ripe_rainbow/runners.py
ripe_rainbow/test_cases.py
ripe_rainbow/util.py
ripe_rainbow/domain/__init__.py
ripe_rainbow/domain/parts.py
ripe_rainbow/domain/wrappers.py
ripe_rainbow/domain/base/__init__.py
ripe_rainbow/domain/base/interactions.py
ripe_rainbow/domain/base/logic.py
ripe_rainbow/domain/base/waits.py
ripe_rainbow/domain/logic/__init__.py
ripe_rainbow/domain/logic/admin.py
ripe_rainbow/domain/logic/provision.py
ripe_rainbow/domain/logic/ripe_copper.py
ripe_rainbow/domain/logic/ripe_core.py
ripe_rainbow/domain/logic/ripe_id.py
ripe_rainbow/domain/logic/ripe_pulse.py
ripe_rainbow/domain/logic/ripe_retail.py
ripe_rainbow/domain/logic/ripe_util_vue.py
ripe_rainbow/domain/logic/ripe_white.py
ripe_rainbow/interactive/__init__.py
ripe_rainbow/interactive/drivers.py
ripe_rainbow/interactive/events.py
ripe_rainbow/interactive/test_cases.py
ripe_rainbow/unit/__init__.py
ripe_rainbow/unit/mock.py
ripe_rainbow/unit/util.py
ripe_rainbow/unit/domain/__init__.py
ripe_rainbow/unit/domain/base/__init__.py
ripe_rainbow/unit/domain/base/logic.py
ripe_rainbow-0.10.3.dist-info/LICENSE
ripe_rainbow-0.10.3.dist-info/METADATA
ripe_rainbow-0.10.3.dist-info/WHEEL
ripe_rainbow-0.10.3.dist-info/entry_points.txt
ripe_rainbow-0.10.3.dist-info/top_level.txt
ripe_rainbow-0.10.3.dist-info/RECORD
